Workbook

Sheet Dashboard
A1: OLIST E-COMMERCE - SALES PERFORMANCE DASHBOARD (2016-2018)
A3: Source: Olist Brazilian E-Commerce Dataset (Kaggle) · Delivered Orders Only · Prepared by: Rifky Mardiansyah · rifkymardiansyah.my.id
A5: Total Revenue (BRL) | E5: Delivered Orders | I5: Total Items Sold | L5: Avg Order Value (BRL)
A7: ='Monthly Summary'!H39 -> 15419774 | E7: ='Monthly Summary'!D39 -> 96478 | I7: ='Category Summary'!E76 -> 110197 | L7: ='Monthly Summary'!I39 -> 159.82684
A11: Monthly Revenue & Orders | I11: Top 10 Categories by Revenue
A12: Year | B12: Month | C12: Orders | D12: Items | E12: Price Rev (BRL) | F12: Freight (BRL) | G12: Total Rev (BRL) | I12: Rank | J12: Category | K12: Orders | L12: Items | M12: Revenue (BRL) | N12: % of Total
A13: ='Monthly Summary'!A3 -> 2016 | B13: ='Monthly Summary'!C3 -> Jan | C13: ='Monthly Summary'!D3 -> 0 | D13: ='Monthly Summary'!E3 -> 0 | E13: ='Monthly Summary'!F3 -> 0 | F13: ='Monthly Summary'!G3 -> 0 | G13: ='Monthly Summary'!H3 -> 0 | I13: ='Category Summary'!A3 -> 1 | J13: ='Category Summary'!B3 -> Health Beauty | K13: ='Category Summary'!D3 -> 8647 | L13: ='Category Summary'!E3 -> 9465 | M13: ='Category Summary'!F3 -> 1412089.5 | N13: ='Category Summary'!H3 -> 0.09157654
A14: ='Monthly Summary'!A4 -> 2016 | B14: ='Monthly Summary'!C4 -> Feb | C14: ='Monthly Summary'!D4 -> 0 | D14: ='Monthly Summary'!E4 -> 0 | E14: ='Monthly Summary'!F4 -> 0 | F14: ='Monthly Summary'!G4 -> 0 | G14: ='Monthly Summary'!H4 -> 0 | I14: ='Category Summary'!A4 -> 2 | J14: ='Category Summary'!B4 -> Watches Gifts | K14: ='Category Summary'!D4 -> 5495 | L14: ='Category Summary'!E4 -> 5859 | M14: ='Category Summary'!F4 -> 1264333.1 | N14: ='Category Summary'!H4 -> 0.081994272
A15: ='Monthly Summary'!A5 -> 2016 | B15: ='Monthly Summary'!C5 -> Mar | C15: ='Monthly Summary'!D5 -> 0 | D15: ='Monthly Summary'!E5 -> 0 | E15: ='Monthly Summary'!F5 -> 0 | F15: ='Monthly Summary'!G5 -> 0 | G15: ='Monthly Summary'!H5 -> 0 | I15: ='Category Summary'!A5 -> 3 | J15: ='Category Summary'!B5 -> Bed Bath Table | K15: ='Category Summary'!D5 -> 9272 | L15: ='Category Summary'!E5 -> 10953 | M15: ='Category Summary'!F5 -> 1225209.3 | N15: ='Category Summary'!H5 -> 0.079457019
A16: ='Monthly Summary'!A6 -> 2016 | B16: ='Monthly Summary'!C6 -> Apr | C16: ='Monthly Summary'!D6 -> 0 | D16: ='Monthly Summary'!E6 -> 0 | E16: ='Monthly Summary'!F6 -> 0 | F16: ='Monthly Summary'!G6 -> 0 | G16: ='Monthly Summary'!H6 -> 0 | I16: ='Category Summary'!A6 -> 4 | J16: ='Category Summary'!B6 -> Sports Leisure | K16: ='Category Summary'!D6 -> 7530 | L16: ='Category Summary'!E6 -> 8431 | M16: ='Category Summary'!F6 -> 1118256.9 | N16: ='Category Summary'!H6 -> 0.072520967
A17: ='Monthly Summary'!A7 -> 2016 | B17: ='Monthly Summary'!C7 -> May | C17: ='Monthly Summary'!D7 -> 0 | D17: ='Monthly Summary'!E7 -> 0 | E17: ='Monthly Summary'!F7 -> 0 | F17: ='Monthly Summary'!G7 -> 0 | G17: ='Monthly Summary'!H7 -> 0 | I17: ='Category Summary'!A7 -> 5 | J17: ='Category Summary'!B7 -> Computers Accessories | K17: ='Category Summary'!D7 -> 6530 | L17: ='Category Summary'!E7 -> 7644 | M17: ='Category Summary'!F7 -> 1032723.8 | N17: ='Category Summary'!H7 -> 0.06697399
A18: ='Monthly Summary'!A8 -> 2016 | B18: ='Monthly Summary'!C8 -> Jun | C18: ='Monthly Summary'!D8 -> 0 | D18: ='Monthly Summary'!E8 -> 0 | E18: ='Monthly Summary'!F8 -> 0 | F18: ='Monthly Summary'!G8 -> 0 | G18: ='Monthly Summary'!H8 -> 0 | I18: ='Category Summary'!A8 -> 6 | J18: ='Category Summary'!B8 -> Furniture Decor | K18: ='Category Summary'!D8 -> 6307 | L18: ='Category Summary'!E8 -> 8160 | M18: ='Category Summary'!F8 -> 880329.92 | N18: ='Category Summary'!H8 -> 0.057090975
A19: ='Monthly Summary'!A9 -> 2016 | B19: ='Monthly Summary'!C9 -> Jul | C19: ='Monthly Summary'!D9 -> 0 | D19: ='Monthly Summary'!E9 -> 0 | E19: ='Monthly Summary'!F9 -> 0 | F19: ='Monthly Summary'!G9 -> 0 | G19: ='Monthly Summary'!H9 -> 0 | I19: ='Category Summary'!A9 -> 7 | J19: ='Category Summary'!B9 -> Housewares | K19: ='Category Summary'!D9 -> 5743 | L19: ='Category Summary'!E9 -> 6795 | M19: ='Category Summary'!F9 -> 758392.25 | N19: ='Category Summary'!H9 -> 0.049183098
A20: ='Monthly Summary'!A10 -> 2016 | B20: ='Monthly Summary'!C10 -> Aug | C20: ='Monthly Summary'!D10 -> 0 | D20: ='Monthly Summary'!E10 -> 0 | E20: ='Monthly Summary'!F10 -> 0 | F20: ='Monthly Summary'!G10 -> 0 | G20: ='Monthly Summary'!H10 -> 0 | I20: ='Category Summary'!A10 -> 8 | J20: ='Category Summary'!B10 -> Cool Stuff | K20: ='Category Summary'!D10 -> 3559 | L20: ='Category Summary'!E10 -> 3718 | M20: ='Category Summary'!F10 -> 691680.89 | N20: ='Category Summary'!H10 -> 0.044856747
A21: ='Monthly Summary'!A11 -> 2016 | B21: ='Monthly Summary'!C11 -> Sep | C21: ='Monthly Summary'!D11 -> 1 | D21: ='Monthly Summary'!E11 -> 3 | E21: ='Monthly Summary'!F11 -> 134.97 | F21: ='Monthly Summary'!G11 -> 8.49 | G21: ='Monthly Summary'!H11 -> 143.46 | I21: ='Category Summary'!A11 -> 9 | J21: ='Category Summary'!B11 -> Auto | K21: ='Category Summary'!D11 -> 3810 | L21: ='Category Summary'!E11 -> 4140 | M21: ='Category Summary'!F11 -> 669454.75 | N21: ='Category Summary'!H11 -> 0.043415342
A22: ='Monthly Summary'!A12 -> 2016 | B22: ='Monthly Summary'!C12 -> Oct | C22: ='Monthly Summary'!D12 -> 265 | D22: ='Monthly Summary'!E12 -> 313 | E22: ='Monthly Summary'!F12 -> 40325.11 | F22: ='Monthly Summary'!G12 -> 6165.55 | G22: ='Monthly Summary'!H12 -> 46490.66 | I22: ='Category Summary'!A12 -> 10 | J22: ='Category Summary'!B12 -> Garden Tools | K22: ='Category Summary'!D12 -> 3448 | L22: ='Category Summary'!E12 -> 4268 | M22: ='Category Summary'!F12 -> 567145.68 | N22: ='Category Summary'!H12 -> 0.036780415
A23: ='Monthly Summary'!A13 -> 2016 | B23: ='Monthly Summary'!C13 -> Nov | C23: ='Monthly Summary'!D13 -> 0 | D23: ='Monthly Summary'!E13 -> 0 | E23: ='Monthly Summary'!F13 -> 0 | F23: ='Monthly Summary'!G13 -> 0 | G23: ='Monthly Summary'!H13 -> 0
A24: ='Monthly Summary'!A14 -> 2016 | B24: ='Monthly Summary'!C14 -> Dec | C24: ='Monthly Summary'!D14 -> 1 | D24: ='Monthly Summary'!E14 -> 1 | E24: ='Monthly Summary'!F14 -> 10.9 | F24: ='Monthly Summary'!G14 -> 8.72 | G24: ='Monthly Summary'!H14 -> 19.62
A25: ='Monthly Summary'!A15 -> 2017 | B25: ='Monthly Summary'!C15 -> Jan | C25: ='Monthly Summary'!D15 -> 750 | D25: ='Monthly Summary'!E15 -> 913 | E25: ='Monthly Summary'!F15 -> 111798.36 | F25: ='Monthly Summary'!G15 -> 15684.01 | G25: ='Monthly Summary'!H15 -> 127482.37
A26: ='Monthly Summary'!A16 -> 2017 | B26: ='Monthly Summary'!C16 -> Feb | C26: ='Monthly Summary'!D16 -> 1653 | D26: ='Monthly Summary'!E16 -> 1858 | E26: ='Monthly Summary'!F16 -> 234223.4 | F26: ='Monthly Summary'!G16 -> 37015.92 | G26: ='Monthly Summary'!H16 -> 271239.32
A27: ='Monthly Summary'!A17 -> 2017 | B27: ='Monthly Summary'!C17 -> Mar | C27: ='Monthly Summary'!D17 -> 2546 | D27: ='Monthly Summary'!E17 -> 2897 | E27: ='Monthly Summary'!F17 -> 359198.85 | F27: ='Monthly Summary'!G17 -> 55132.1 | G27: ='Monthly Summary'!H17 -> 414330.95
A28: ='Monthly Summary'!A18 -> 2017 | B28: ='Monthly Summary'!C18 -> Apr | C28: ='Monthly Summary'!D18 -> 2303 | D28: ='Monthly Summary'!E18 -> 2569 | E28: ='Monthly Summary'!F18 -> 340669.68 | F28: ='Monthly Summary'!G18 -> 50142.72 | G28: ='Monthly Summary'!H18 -> 390812.4
A29: ='Monthly Summary'!A19 -> 2017 | B29: ='Monthly Summary'!C19 -> May | C29: ='Monthly Summary'!D19 -> 3546 | D29: ='Monthly Summary'!E19 -> 4004 | E29: ='Monthly Summary'!F19 -> 489338.25 | F29: ='Monthly Summary'!G19 -> 77513.15 | G29: ='Monthly Summary'!H19 -> 566851.4
A30: ='Monthly Summary'!A20 -> 2017 | B30: ='Monthly Summary'!C20 -> Jun | C30: ='Monthly Summary'!D20 -> 3135 | D30: ='Monthly Summary'!E20 -> 3489 | E30: ='Monthly Summary'!F20 -> 421923.37 | F30: ='Monthly Summary'!G20 -> 68127 | G30: ='Monthly Summary'!H20 -> 490050.37
A31: ='Monthly Summary'!A21 -> 2017 | B31: ='Monthly Summary'!C21 -> Jul | C31: ='Monthly Summary'!D21 -> 3872 | D31: ='Monthly Summary'!E21 -> 4416 | E31: ='Monthly Summary'!F21 -> 481604.52 | F31: ='Monthly Summary'!G21 -> 84694.56 | G31: ='Monthly Summary'!H21 -> 566299.08
A32: ='Monthly Summary'!A22 -> 2017 | B32: ='Monthly Summary'!C22 -> Aug | C32: ='Monthly Summary'!D22 -> 4193 | D32: ='Monthly Summary'!E22 -> 4797 | E32: ='Monthly Summary'!F22 -> 554699.7 | F32: ='Monthly Summary'!G22 -> 91132.66 | G32: ='Monthly Summary'!H22 -> 645832.36
A33: ='Monthly Summary'!A23 -> 2017 | B33: ='Monthly Summary'!C23 -> Sep | C33: ='Monthly Summary'!D23 -> 4150 | D33: ='Monthly Summary'!E23 -> 4737 | E33: ='Monthly Summary'!F23 -> 607399.67 | F33: ='Monthly Summary'!G23 -> 93677.82 | G33: ='Monthly Summary'!H23 -> 701077.49
A34: ='Monthly Summary'!A24 -> 2017 | B34: ='Monthly Summary'!C24 -> Oct | C34: ='Monthly Summary'!D24 -> 4478 | D34: ='Monthly Summary'!E24 -> 5214 | E34: ='Monthly Summary'!F24 -> 648247.65 | F34: ='Monthly Summary'!G24 -> 102869.36 | G34: ='Monthly Summary'!H24 -> 751117.01
... A48: ='Monthly Summary'!A38 -> 2018 | B48: ='Monthly Summary'!C38 -> Dec | C48: ='Monthly Summary'!D38 -> 0 | D48: ='Monthly Summary'!E38 -> 0 | E48: ='Monthly Summary'!F38 -> 0 | F48: ='Monthly Summary'!G38 -> 0 | G48: ='Monthly Summary'!H38 -> 0
A49: TOTAL | B49: - | C49: ='Monthly Summary'!D39 -> 96478 | D49: ='Monthly Summary'!E39 -> 110197 | E49: ='Monthly Summary'!F39 -> 13221498 | F49: ='Monthly Summary'!G39 -> 2198275.6 | G49: ='Monthly Summary'!H39 -> 15419774
A51: Year-on-Year Growth
A52: Year | B52: Orders | C52: Revenue (BRL) | D52: YoY Orders | E52: YoY Revenue
A53: ='Monthly Summary'!A43 -> 2016 | B53: ='Monthly Summary'!B43 -> 267 | C53: ='Monthly Summary'!C43 -> 46653.74 | D53: First Year | E53: First Year
A54: ='Monthly Summary'!A44 -> 2017 | B54: ='Monthly Summary'!B44 -> 43428 | C54: ='Monthly Summary'!C44 -> 6921535.2 | D54: ='Monthly Summary'!D44 -> 161.65169 | E54: ='Monthly Summary'!E44 -> 147.35971
A55: ='Monthly Summary'!A45 -> 2018 | B55: ='Monthly Summary'!B45 -> 52783 | C55: ='Monthly Summary'!C45 -> 8451584.8 | D55: ='Monthly Summary'!D45 -> 0.21541402 | E55: ='Monthly Summary'!E45 -> 0.22105638

Sheet Data - Monthly
A1: MONTHLY AGGREGATED DATA
A2: Year | B2: MonthNo | C2: MonthName | D2: Orders | E2: Items | F2: Price Sum | G2: Freight Sum | H2: Total Revenue
A3: 2016 | B3: 1 | C3: Jan | D3: 0 | E3: 0 | F3: 0 | G3: 0 | H3: 0
A4: 2016 | B4: 2 | C4: Feb | D4: 0 | E4: 0 | F4: 0 | G4: 0 | H4: 0
A5: 2016 | B5: 3 | C5: Mar | D5: 0 | E5: 0 | F5: 0 | G5: 0 | H5: 0
A6: 2016 | B6: 4 | C6: Apr | D6: 0 | E6: 0 | F6: 0 | G6: 0 | H6: 0
A7: 2016 | B7: 5 | C7: May | D7: 0 | E7: 0 | F7: 0 | G7: 0 | H7: 0
A8: 2016 | B8: 6 | C8: Jun | D8: 0 | E8: 0 | F8: 0 | G8: 0 | H8: 0
A9: 2016 | B9: 7 | C9: Jul | D9: 0 | E9: 0 | F9: 0 | G9: 0 | H9: 0
A10: 2016 | B10: 8 | C10: Aug | D10: 0 | E10: 0 | F10: 0 | G10: 0 | H10: 0
A11: 2016 | B11: 9 | C11: Sep | D11: 1 | E11: 3 | F11: 134.97 | G11: 8.49 | H11: 143.46
A12: 2016 | B12: 10 | C12: Oct | D12: 265 | E12: 313 | F12: 40325.11 | G12: 6165.55 | H12: 46490.66
A13: 2016 | B13: 11 | C13: Nov | D13: 0 | E13: 0 | F13: 0 | G13: 0 | H13: 0
A14: 2016 | B14: 12 | C14: Dec | D14: 1 | E14: 1 | F14: 10.9 | G14: 8.72 | H14: 19.62
... A38: 2018 | B38: 12 | C38: Dec | D38: 0 | E38: 0 | F38: 0 | G38: 0 | H38: 0
A39: TOTAL | D39: =SUM(D3:D38) -> 96478 | E39: =SUM(E3:E38) -> 110197 | F39: =SUM(F3:F38) -> 13221498 | G39: =SUM(G3:G38) -> 2198275.6 | H39: =SUM(H3:H38) -> 15419774

Sheet Data - Category
A1: CATEGORY AGGREGATED DATA
A2: Rank | B2: Category (English) | C2: Category (Portuguese) | D2: Orders | E2: Items | F2: Revenue (BRL) | G2: Avg Item Price (BRL)
A3: 1 | B3: Health Beauty | C3: beleza_saude | D3: 8647 | E3: 9465 | F3: 1412089.5 | G3: 149.19
A4: 2 | B4: Watches Gifts | C4: relogios_presentes | D4: 5495 | E4: 5859 | F4: 1264333.1 | G4: 215.79
A5: 3 | B5: Bed Bath Table | C5: cama_mesa_banho | D5: 9272 | E5: 10953 | F5: 1225209.3 | G5: 111.86
A6: 4 | B6: Sports Leisure | C6: esporte_lazer | D6: 7530 | E6: 8431 | F6: 1118256.9 | G6: 132.64
A7: 5 | B7: Computers Accessories | C7: informatica_acessorios | D7: 6530 | E7: 7644 | F7: 1032723.8 | G7: 135.1
A8: 6 | B8: Furniture Decor | C8: moveis_decoracao | D8: 6307 | E8: 8160 | F8: 880329.92 | G8: 107.88
A9: 7 | B9: Housewares | C9: utilidades_domesticas | D9: 5743 | E9: 6795 | F9: 758392.25 | G9: 111.61
A10: 8 | B10: Cool Stuff | C10: cool_stuff | D10: 3559 | E10: 3718 | F10: 691680.89 | G10: 186.04
A11: 9 | B11: Auto | C11: automotivo | D11: 3810 | E11: 4140 | F11: 669454.75 | G11: 161.7
A12: 10 | B12: Garden Tools | C12: ferramentas_jardim | D12: 3448 | E12: 4268 | F12: 567145.68 | G12: 132.88
A13: 11 | B13: Toys | C13: brinquedos | D13: 3804 | E13: 4030 | F13: 547061.06 | G13: 135.75
A14: 12 | B14: Baby | C14: bebes | D14: 2809 | E14: 2982 | F14: 466727.65 | G14: 156.51
... A74: 72 | B74: Security And Services | C74: seguros_e_servicos | D74: 2 | E74: 2 | F74: 324.51 | G74: 162.26
A75: TOTAL | B75: ALL CATEGORIES | D75: =SUM(D3:D74) -> 97276 | E75: =SUM(E3:E74) -> 110197 | F75: =SUM(F3:F74) -> 15419774 | G75: =IF(E75=0,0,F75/E75) -> 139.92916

Sheet Monthly Summary
A1: MONTHLY SALES SUMMARY - OLIST E-COMMERCE (DELIVERED ORDERS ONLY)
A2: Year | B2: MonthNo | C2: Month | D2: Total Orders | E2: Items Sold | F2: Price Revenue (BRL) | G2: Freight Revenue (BRL) | H2: Total Revenue (BRL) | I2: Avg Order Value (BRL)
A3: ='Data - Monthly'!A3 -> 2016 | B3: ='Data - Monthly'!B3 -> 1 | C3: ='Data - Monthly'!C3 -> Jan | D3: ='Data - Monthly'!D3 -> 0 | E3: ='Data - Monthly'!E3 -> 0 | F3: ='Data - Monthly'!F3 -> 0 | G3: ='Data - Monthly'!G3 -> 0 | H3: ='Data - Monthly'!H3 -> 0 | I3: =IF(D3=0,0,H3/D3) -> 0
A4: ='Data - Monthly'!A4 -> 2016 | B4: ='Data - Monthly'!B4 -> 2 | C4: ='Data - Monthly'!C4 -> Feb | D4: ='Data - Monthly'!D4 -> 0 | E4: ='Data - Monthly'!E4 -> 0 | F4: ='Data - Monthly'!F4 -> 0 | G4: ='Data - Monthly'!G4 -> 0 | H4: ='Data - Monthly'!H4 -> 0 | I4: =IF(D4=0,0,H4/D4) -> 0
A5: ='Data - Monthly'!A5 -> 2016 | B5: ='Data - Monthly'!B5 -> 3 | C5: ='Data - Monthly'!C5 -> Mar | D5: ='Data - Monthly'!D5 -> 0 | E5: ='Data - Monthly'!E5 -> 0 | F5: ='Data - Monthly'!F5 -> 0 | G5: ='Data - Monthly'!G5 -> 0 | H5: ='Data - Monthly'!H5 -> 0 | I5: =IF(D5=0,0,H5/D5) -> 0
A6: ='Data - Monthly'!A6 -> 2016 | B6: ='Data - Monthly'!B6 -> 4 | C6: ='Data - Monthly'!C6 -> Apr | D6: ='Data - Monthly'!D6 -> 0 | E6: ='Data - Monthly'!E6 -> 0 | F6: ='Data - Monthly'!F6 -> 0 | G6: ='Data - Monthly'!G6 -> 0 | H6: ='Data - Monthly'!H6 -> 0 | I6: =IF(D6=0,0,H6/D6) -> 0
A7: ='Data - Monthly'!A7 -> 2016 | B7: ='Data - Monthly'!B7 -> 5 | C7: ='Data - Monthly'!C7 -> May | D7: ='Data - Monthly'!D7 -> 0 | E7: ='Data - Monthly'!E7 -> 0 | F7: ='Data - Monthly'!F7 -> 0 | G7: ='Data - Monthly'!G7 -> 0 | H7: ='Data - Monthly'!H7 -> 0 | I7: =IF(D7=0,0,H7/D7) -> 0
A8: ='Data - Monthly'!A8 -> 2016 | B8: ='Data - Monthly'!B8 -> 6 | C8: ='Data - Monthly'!C8 -> Jun | D8: ='Data - Monthly'!D8 -> 0 | E8: ='Data - Monthly'!E8 -> 0 | F8: ='Data - Monthly'!F8 -> 0 | G8: ='Data - Monthly'!G8 -> 0 | H8: ='Data - Monthly'!H8 -> 0 | I8: =IF(D8=0,0,H8/D8) -> 0
A9: ='Data - Monthly'!A9 -> 2016 | B9: ='Data - Monthly'!B9 -> 7 | C9: ='Data - Monthly'!C9 -> Jul | D9: ='Data - Monthly'!D9 -> 0 | E9: ='Data - Monthly'!E9 -> 0 | F9: ='Data - Monthly'!F9 -> 0 | G9: ='Data - Monthly'!G9 -> 0 | H9: ='Data - Monthly'!H9 -> 0 | I9: =IF(D9=0,0,H9/D9) -> 0
A10: ='Data - Monthly'!A10 -> 2016 | B10: ='Data - Monthly'!B10 -> 8 | C10: ='Data - Monthly'!C10 -> Aug | D10: ='Data - Monthly'!D10 -> 0 | E10: ='Data - Monthly'!E10 -> 0 | F10: ='Data - Monthly'!F10 -> 0 | G10: ='Data - Monthly'!G10 -> 0 | H10: ='Data - Monthly'!H10 -> 0 | I10: =IF(D10=0,0,H10/D10) -> 0
A11: ='Data - Monthly'!A11 -> 2016 | B11: ='Data - Monthly'!B11 -> 9 | C11: ='Data - Monthly'!C11 -> Sep | D11: ='Data - Monthly'!D11 -> 1 | E11: ='Data - Monthly'!E11 -> 3 | F11: ='Data - Monthly'!F11 -> 134.97 | G11: ='Data - Monthly'!G11 -> 8.49 | H11: ='Data - Monthly'!H11 -> 143.46 | I11: =IF(D11=0,0,H11/D11) -> 143.46
A12: ='Data - Monthly'!A12 -> 2016 | B12: ='Data - Monthly'!B12 -> 10 | C12: ='Data - Monthly'!C12 -> Oct | D12: ='Data - Monthly'!D12 -> 265 | E12: ='Data - Monthly'!E12 -> 313 | F12: ='Data - Monthly'!F12 -> 40325.11 | G12: ='Data - Monthly'!G12 -> 6165.55 | H12: ='Data - Monthly'!H12 -> 46490.66 | I12: =IF(D12=0,0,H12/D12) -> 175.43645
A13: ='Data - Monthly'!A13 -> 2016 | B13: ='Data - Monthly'!B13 -> 11 | C13: ='Data - Monthly'!C13 -> Nov | D13: ='Data - Monthly'!D13 -> 0 | E13: ='Data - Monthly'!E13 -> 0 | F13: ='Data - Monthly'!F13 -> 0 | G13: ='Data - Monthly'!G13 -> 0 | H13: ='Data - Monthly'!H13 -> 0 | I13: =IF(D13=0,0,H13/D13) -> 0
A14: ='Data - Monthly'!A14 -> 2016 | B14: ='Data - Monthly'!B14 -> 12 | C14: ='Data - Monthly'!C14 -> Dec | D14: ='Data - Monthly'!D14 -> 1 | E14: ='Data - Monthly'!E14 -> 1 | F14: ='Data - Monthly'!F14 -> 10.9 | G14: ='Data - Monthly'!G14 -> 8.72 | H14: ='Data - Monthly'!H14 -> 19.62 | I14: =IF(D14=0,0,H14/D14) -> 19.62
... A38: ='Data - Monthly'!A38 -> 2018 | B38: ='Data - Monthly'!B38 -> 12 | C38: ='Data - Monthly'!C38 -> Dec | D38: ='Data - Monthly'!D38 -> 0 | E38: ='Data - Monthly'!E38 -> 0 | F38: ='Data - Monthly'!F38 -> 0 | G38: ='Data - Monthly'!G38 -> 0 | H38: ='Data - Monthly'!H38 -> 0 | I38: =IF(D38=0,0,H38/D38) -> 0
A39: TOTAL | B39: — | C39: — | D39: =SUM(D3:D38) -> 96478 | E39: =SUM(E3:E38) -> 110197 | F39: =SUM(F3:F38) -> 13221498 | G39: =SUM(G3:G38) -> 2198275.6 | H39: =SUM(H3:H38) -> 15419774 | I39: =IF(D39=0,0,H39/D39) -> 159.82684
A41: YEAR-ON-YEAR PERFORMANCE
A42: Year | B42: Total Orders | C42: Total Revenue (BRL) | D42: YoY Order Growth | E42: YoY Revenue Growth
A43: 2016 | B43: =SUMIF(A3:A38,2016,D3:D38) -> 267 | C43: =SUMIF(A3:A38,2016,H3:H38) -> 46653.74 | D43: — | E43: —
A44: 2017 | B44: =SUMIF(A3:A38,2017,D3:D38) -> 43428 | C44: =SUMIF(A3:A38,2017,H3:H38) -> 6921535.2 | D44: =IF(B43=0,0,(B44-B43)/B43) -> 161.65169 | E44: =IF(C43=0,0,(C44-C43)/C43) -> 147.35971
A45: 2018 | B45: =SUMIF(A3:A38,2018,D3:D38) -> 52783 | C45: =SUMIF(A3:A38,2018,H3:H38) -> 8451584.8 | D45: =IF(B44=0,0,(B45-B44)/B44) -> 0.21541402 | E45: =IF(C44=0,0,(C45-C44)/C44) -> 0.22105638

Sheet Category Summary
A1: PRODUCT CATEGORY PERFORMANCE - FORMULA-BASED
A2: Rank | B2: Category (English) | C2: Category (Portuguese) | D2: Orders | E2: Items Sold | F2: Revenue (BRL) | G2: Avg Item Price (BRL) | H2: % of Total Revenue
A3: ='Data - Category'!A3 -> 1 | B3: ='Data - Category'!B3 -> Health Beauty | C3: ='Data - Category'!C3 -> beleza_saude | D3: ='Data - Category'!D3 -> 8647 | E3: ='Data - Category'!E3 -> 9465 | F3: ='Data - Category'!F3 -> 1412089.5 | G3: =IF(E3=0,0,F3/E3) -> 149.19065 | H3: =IF(F$76=0,0,F3/F$76) -> 0.09157654
A4: ='Data - Category'!A4 -> 2 | B4: ='Data - Category'!B4 -> Watches Gifts | C4: ='Data - Category'!C4 -> relogios_presentes | D4: ='Data - Category'!D4 -> 5495 | E4: ='Data - Category'!E4 -> 5859 | F4: ='Data - Category'!F4 -> 1264333.1 | G4: =IF(E4=0,0,F4/E4) -> 215.79333 | H4: =IF(F$76=0,0,F4/F$76) -> 0.081994272
A5: ='Data - Category'!A5 -> 3 | B5: ='Data - Category'!B5 -> Bed Bath Table | C5: ='Data - Category'!C5 -> cama_mesa_banho | D5: ='Data - Category'!D5 -> 9272 | E5: ='Data - Category'!E5 -> 10953 | F5: ='Data - Category'!F5 -> 1225209.3 | G5: =IF(E5=0,0,F5/E5) -> 111.86061 | H5: =IF(F$76=0,0,F5/F$76) -> 0.079457019
A6: ='Data - Category'!A6 -> 4 | B6: ='Data - Category'!B6 -> Sports Leisure | C6: ='Data - Category'!C6 -> esporte_lazer | D6: ='Data - Category'!D6 -> 7530 | E6: ='Data - Category'!E6 -> 8431 | F6: ='Data - Category'!F6 -> 1118256.9 | G6: =IF(E6=0,0,F6/E6) -> 132.63633 | H6: =IF(F$76=0,0,F6/F$76) -> 0.072520967
A7: ='Data - Category'!A7 -> 5 | B7: ='Data - Category'!B7 -> Computers Accessories | C7: ='Data - Category'!C7 -> informatica_acessorios | D7: ='Data - Category'!D7 -> 6530 | E7: ='Data - Category'!E7 -> 7644 | F7: ='Data - Category'!F7 -> 1032723.8 | G7: =IF(E7=0,0,F7/E7) -> 135.10253 | H7: =IF(F$76=0,0,F7/F$76) -> 0.06697399
A8: ='Data - Category'!A8 -> 6 | B8: ='Data - Category'!B8 -> Furniture Decor | C8: ='Data - Category'!C8 -> moveis_decoracao | D8: ='Data - Category'!D8 -> 6307 | E8: ='Data - Category'!E8 -> 8160 | F8: ='Data - Category'!F8 -> 880329.92 | G8: =IF(E8=0,0,F8/E8) -> 107.88357 | H8: =IF(F$76=0,0,F8/F$76) -> 0.057090975
A9: ='Data - Category'!A9 -> 7 | B9: ='Data - Category'!B9 -> Housewares | C9: ='Data - Category'!C9 -> utilidades_domesticas | D9: ='Data - Category'!D9 -> 5743 | E9: ='Data - Category'!E9 -> 6795 | F9: ='Data - Category'!F9 -> 758392.25 | G9: =IF(E9=0,0,F9/E9) -> 111.61034 | H9: =IF(F$76=0,0,F9/F$76) -> 0.049183098
A10: ='Data - Category'!A10 -> 8 | B10: ='Data - Category'!B10 -> Cool Stuff | C10: ='Data - Category'!C10 -> cool_stuff | D10: ='Data - Category'!D10 -> 3559 | E10: ='Data - Category'!E10 -> 3718 | F10: ='Data - Category'!F10 -> 691680.89 | G10: =IF(E10=0,0,F10/E10) -> 186.03574 | H10: =IF(F$76=0,0,F10/F$76) -> 0.044856747
A11: ='Data - Category'!A11 -> 9 | B11: ='Data - Category'!B11 -> Auto | C11: ='Data - Category'!C11 -> automotivo | D11: ='Data - Category'!D11 -> 3810 | E11: ='Data - Category'!E11 -> 4140 | F11: ='Data - Category'!F11 -> 669454.75 | G11: =IF(E11=0,0,F11/E11) -> 161.70405 | H11: =IF(F$76=0,0,F11/F$76) -> 0.043415342
A12: ='Data - Category'!A12 -> 10 | B12: ='Data - Category'!B12 -> Garden Tools | C12: ='Data - Category'!C12 -> ferramentas_jardim | D12: ='Data - Category'!D12 -> 3448 | E12: ='Data - Category'!E12 -> 4268 | F12: ='Data - Category'!F12 -> 567145.68 | G12: =IF(E12=0,0,F12/E12) -> 132.88324 | H12: =IF(F$76=0,0,F12/F$76) -> 0.036780415
A13: ='Data - Category'!A13 -> 11 | B13: ='Data - Category'!B13 -> Toys | C13: ='Data - Category'!C13 -> brinquedos | D13: ='Data - Category'!D13 -> 3804 | E13: ='Data - Category'!E13 -> 4030 | F13: ='Data - Category'!F13 -> 547061.06 | G13: =IF(E13=0,0,F13/E13) -> 135.74716 | H13: =IF(F$76=0,0,F13/F$76) -> 0.035477891
A14: ='Data - Category'!A14 -> 12 | B14: ='Data - Category'!B14 -> Baby | C14: ='Data - Category'!C14 -> bebes | D14: ='Data - Category'!D14 -> 2809 | E14: ='Data - Category'!E14 -> 2982 | F14: ='Data - Category'!F14 -> 466727.65 | G14: =IF(E14=0,0,F14/E14) -> 156.51497 | H14: =IF(F$76=0,0,F14/F$76) -> 0.030268126
... A74: ='Data - Category'!A74 -> 72 | B74: ='Data - Category'!B74 -> Security And Services | C74: ='Data - Category'!C74 -> seguros_e_servicos | D74: ='Data - Category'!D74 -> 2 | E74: ='Data - Category'!E74 -> 2 | F74: ='Data - Category'!F74 -> 324.51 | G74: =IF(E74=0,0,F74/E74) -> 162.255 | H74: =IF(F$76=0,0,F74/F$76) -> 2.1045056e-05
A76: TOTAL | B76: ALL CATEGORIES | D76: =SUM(D3:D75) -> 97276 | E76: =SUM(E3:E75) -> 110197 | F76: =SUM(F3:F75) -> 15419774 | G76: =IF(E76=0,0,F76/E76) -> 139.92916 | H76: 100.00%
